girder_style/__init__.py
girder_style/apps.py
girder_style/static/girder_style/styles.css
girder_style/static/girder_style/styles.css.map
girder_style/templates/account/account_inactive.html
girder_style/templates/account/base.html
girder_style/templates/account/email.html
girder_style/templates/account/email_confirm.html
girder_style/templates/account/login.html
girder_style/templates/account/logout.html
girder_style/templates/account/password_change.html
girder_style/templates/account/password_reset.html
girder_style/templates/account/password_reset_done.html
girder_style/templates/account/password_reset_from_key.html
girder_style/templates/account/password_reset_from_key_done.html
girder_style/templates/account/password_set.html
girder_style/templates/account/signup.html
girder_style/templates/account/signup_closed.html
girder_style/templates/account/verification_sent.html
girder_style/templates/account/verified_email_required.html
girder_style/templates/account/email/base_message.txt
girder_style/templates/account/email/email_confirmation_message.txt
girder_style/templates/account/email/email_confirmation_signup_message.txt
girder_style/templates/account/email/email_confirmation_signup_subject.txt
girder_style/templates/account/email/email_confirmation_subject.txt
girder_style/templates/account/email/password_reset_key_message.txt
girder_style/templates/account/email/password_reset_key_subject.txt
girder_style/templates/account/snippets/already_logged_in.html
girder_style/templates/account/snippets/menu_item.html
girder_style/templates/account/snippets/message_item.html
girder_style/templates/account/snippets/sub_menu_item.html
girder_style/templates/girder_style/base.html
girder_style/templates/socialaccount/snippets/provider_list.html
django_girder_style-0.7.1.dist-info/LICENSE
django_girder_style-0.7.1.dist-info/METADATA
django_girder_style-0.7.1.dist-info/WHEEL
django_girder_style-0.7.1.dist-info/top_level.txt
django_girder_style-0.7.1.dist-info/RECORD
